[
  {
    "name": "Korg_DDM110",
    "pads": [
      {
        "button": "q",
        "audioName": "ddm-bd",
        "src": "/static/media/sounds/Korg_DDM110/ddm-bd.wav"
      },
      {
        "button": "w",
        "audioName": "ddm-ch",
        "src": "/static/media/sounds/Korg_DDM110/ddm-ch.wav"
      },
      {
        "button": "e",
        "audioName": "ddm-cp",
        "src": "/static/media/sounds/Korg_DDM110/ddm-cp.wav"
      },
      {
        "button": "a",
        "audioName": "ddm-cy",
        "src": "/static/media/sounds/Korg_DDM110/ddm-cy.wav"
      },
      {
        "button": "s",
        "audioName": "ddm-ht",
        "src": "/static/media/sounds/Korg_DDM110/ddm-ht.wav"
      },
      {
        "button": "d",
        "audioName": "ddm-lt",
        "src": "/static/media/sounds/Korg_DDM110/ddm-lt.wav"
      },
      {
        "button": "z",
        "audioName": "ddm-oh",
        "src": "/static/media/sounds/Korg_DDM110/ddm-oh.wav"
      },
      {
        "button": "x",
        "audioName": "ddm-rs",
        "src": "/static/media/sounds/Korg_DDM110/ddm-rs.wav"
      },
      {
        "button": "c",
        "audioName": "ddm-sd",
        "src": "/static/media/sounds/Korg_DDM110/ddm-sd.wav"
      }
    ]
  },
  {
    "name": "MTI_AO-1",
    "pads": [
      {
        "button": "q",
        "audioName": "mtibongo",
        "src": "/static/media/sounds/MTI_AO-1/mtibongo.wav"
      },
      {
        "button": "w",
        "audioName": "mticlave",
        "src": "/static/media/sounds/MTI_AO-1/mticlave.wav"
      },
      {
        "button": "e",
        "audioName": "mticonga",
        "src": "/static/media/sounds/MTI_AO-1/mticonga.wav"
      },
      {
        "button": "a",
        "audioName": "mticow",
        "src": "/static/media/sounds/MTI_AO-1/mticow.wav"
      },
      {
        "button": "s",
        "audioName": "mticymb1",
        "src": "/static/media/sounds/MTI_AO-1/mticymb1.wav"
      },
      {
        "button": "d",
        "audioName": "mticymb2",
        "src": "/static/media/sounds/MTI_AO-1/mticymb2.wav"
      },
      {
        "button": "z",
        "audioName": "mtihh",
        "src": "/static/media/sounds/MTI_AO-1/mtihh.wav"
      },
      {
        "button": "x",
        "audioName": "mtikick",
        "src": "/static/media/sounds/MTI_AO-1/mtikick.wav"
      },
      {
        "button": "c",
        "audioName": "mtisnare",
        "src": "/static/media/sounds/MTI_AO-1/mtisnare.wav"
      }
    ]
  },
  {
    "name": "YamahaCS-40M",
    "pads": [
      {
        "button": "q",
        "audioName": "Bell",
        "src": "/static/media/sounds/YamahaCS-40M/Bell.wav"
      },
      {
        "button": "w",
        "audioName": "Cymbal-1",
        "src": "/static/media/sounds/YamahaCS-40M/Cymbal-1.wav"
      },
      {
        "button": "e",
        "audioName": "Cymbal-2",
        "src": "/static/media/sounds/YamahaCS-40M/Cymbal-2.wav"
      },
      {
        "button": "a",
        "audioName": "Kick",
        "src": "/static/media/sounds/YamahaCS-40M/Kick.wav"
      },
      {
        "button": "s",
        "audioName": "Klank",
        "src": "/static/media/sounds/YamahaCS-40M/Klank.wav"
      },
      {
        "button": "d",
        "audioName": "Snare-1",
        "src": "/static/media/sounds/YamahaCS-40M/Snare-1.wav"
      },
      {
        "button": "z",
        "audioName": "Snare-2",
        "src": "/static/media/sounds/YamahaCS-40M/Snare-2.wav"
      },
      {
        "button": "x",
        "audioName": "Snare-3",
        "src": "/static/media/sounds/YamahaCS-40M/Snare-3.wav"
      },
      {
        "button": "c",
        "audioName": "Tom",
        "src": "/static/media/sounds/YamahaCS-40M/Tom.wav"
      }
    ]
  }
]
